{
  "version": "1.0.0",
  "lastUpdated": "2026-01-21T00:00:00Z",
  "source": "P4 Proof Vault - FY2026 Strategy Manual",
  "selectionRules": {
    "priority": ["exact_match", "adjacent_match", "generic"],
    "rule": "1 Link + 1 Proof per outreach"
  },
  "kpiTargets": {
    "uses_per_year": 450,
    "vault_to_meeting": 0.20
  },
  "proofs": [
    {
      "id": "proof_001",
      "title": "The Castle - LOD 350 Historic Renovation",
      "name": "The Castle Historic Renovation",
      "pod": "P20",
      "type": "case_study",
      "status": "PRIMARY",
      "building_types": ["Historic", "Residential", "Adaptive Reuse"],
      "buildingTypes": ["Historic", "Residential", "Adaptive Reuse"],
      "sqft": 45000,
      "projectSF": 45000,
      "lod_level": 350,
      "lodLevel": 350,
      "disciplines": ["architecture", "structural", "mep"],
      "thumbnail_url": "/proof/castle_thumb.jpg",
      "pdf_url": "/proof/castle_case_study.pdf",
      "snippet": "45,000 sqft historic castle renovation in the Hudson Valley. ±3mm variance control enabled structural retrofit without demolition. Saved $180K in change orders through accurate existing conditions.",
      "key_stats": {
        "sqft": 45000,
        "savings": "$180,000",
        "timeline": "3 weeks",
        "accuracy": "±3mm"
      },
      "buyerPersonaFit": ["Risk-Averse Principal", "Tech-Forward BIM Director"],
      "awards": [],
      "location": "Hudson Valley, NY",
      "personas": ["BP1_Engineer", "BP5_Architect"],
      "uses": 47,
      "vault_to_meeting": 0.23,
      "last_used": "2026-01-20T00:00:00Z",
      "created_at": "2025-09-15T00:00:00Z"
    },
    {
      "id": "proof_002",
      "title": "CUNY Baruch - LOD 200 Campus Documentation",
      "name": "CUNY Baruch Campus Documentation",
      "pod": "P4",
      "type": "lod_sample",
      "status": "ACTIVE",
      "building_types": ["Education", "Commercial", "Institutional"],
      "buildingTypes": ["Education", "Commercial", "Institutional"],
      "sqft": 785000,
      "projectSF": 785000,
      "lod_level": 200,
      "lodLevel": 200,
      "disciplines": ["architecture"],
      "thumbnail_url": "/proof/cuny_thumb.jpg",
      "pdf_url": "/proof/cuny_lod200_sample.pdf",
      "snippet": "785,000 sqft campus-wide documentation for facilities management. Delivered 17-story vertical building plus 3 adjacent structures in 4 weeks.",
      "key_stats": {
        "sqft": 785000,
        "buildings": 4,
        "timeline": "4 weeks",
        "deliverable": "Revit + Point Cloud"
      },
      "buyerPersonaFit": ["Risk-Averse Principal", "Budget-Conscious PM"],
      "awards": [],
      "location": "New York, NY",
      "personas": ["BP2_Executive", "BP1_Engineer"],
      "uses": 32,
      "vault_to_meeting": 0.19,
      "last_used": "2026-01-18T00:00:00Z",
      "created_at": "2025-06-01T00:00:00Z"
    },
    {
      "id": "proof_003",
      "title": "Mount Sinai Healthcare Retrofit",
      "name": "Mount Sinai Healthcare Retrofit",
      "pod": "P4",
      "type": "lod_sample",
      "status": "ACTIVE",
      "building_types": ["Healthcare", "Commercial", "Adaptive Reuse"],
      "buildingTypes": ["Healthcare", "Commercial", "Adaptive Reuse"],
      "sqft": 150000,
      "projectSF": 150000,
      "lod_level": 350,
      "lodLevel": 350,
      "disciplines": ["architecture", "mep"],
      "thumbnail_url": "/proof/healthcare_thumb.jpg",
      "pdf_url": "/proof/healthcare_lod300.pdf",
      "snippet": "150,000 sqft hospital wing MEP coordination. Captured complex ceiling plenum conditions for mechanical retrofit. Zero RFIs from scan-derived model.",
      "key_stats": {
        "sqft": 150000,
        "rfi_reduction": "100%",
        "timeline": "2 weeks",
        "focus": "MEP Coordination"
      },
      "buyerPersonaFit": ["Risk-Averse Principal", "Tech-Forward BIM Director"],
      "awards": ["2024 AIA Healthcare Design Award"],
      "location": "New York, NY",
      "personas": ["BP1_Engineer"],
      "uses": 28,
      "vault_to_meeting": 0.21,
      "last_used": "2026-01-15T00:00:00Z",
      "created_at": "2025-08-20T00:00:00Z"
    },
    {
      "id": "proof_004",
      "title": "Mixed-Use Tower - LOD 350 Facade Documentation",
      "pod": "P4",
      "type": "lod_sample",
      "status": "ACTIVE",
      "building_types": ["mixed_use", "high_rise", "commercial"],
      "sqft": 320000,
      "lod_level": 350,
      "disciplines": ["architecture", "structural"],
      "thumbnail_url": "/proof/tower_thumb.jpg",
      "pdf_url": "/proof/tower_lod350.pdf",
      "snippet": "320,000 sqft mixed-use tower facade assessment. High-detail exterior scanning for LL11 compliance and facade repair planning.",
      "key_stats": {
        "sqft": 320000,
        "floors": 42,
        "compliance": "LL11",
        "deliverable": "Facade Model + Report"
      },
      "personas": ["BP2_Executive", "BP5_Architect"],
      "uses": 15,
      "vault_to_meeting": 0.27,
      "last_used": "2026-01-10T00:00:00Z",
      "created_at": "2025-11-01T00:00:00Z"
    },
    {
      "id": "proof_005",
      "title": "Variance Control Whitepaper",
      "pod": "P4",
      "type": "whitepaper",
      "status": "ACTIVE",
      "building_types": ["all"],
      "sqft": null,
      "lod_level": null,
      "disciplines": ["general"],
      "thumbnail_url": "/proof/whitepaper_thumb.jpg",
      "pdf_url": "/proof/variance_control_whitepaper.pdf",
      "snippet": "Technical whitepaper: Why ±3mm variance control prevents $50K+ change orders. Includes ROI calculator and case study data.",
      "key_stats": {
        "pages": 12,
        "roi_calculator": true,
        "target_persona": "Executive"
      },
      "personas": ["BP2_Executive"],
      "uses": 89,
      "vault_to_meeting": 0.15,
      "last_used": "2026-01-21T00:00:00Z",
      "created_at": "2025-04-01T00:00:00Z"
    },
    {
      "id": "proof_006",
      "title": "Industrial Facility - Site Topo + Building",
      "pod": "P4",
      "type": "lod_sample",
      "status": "ACTIVE",
      "building_types": ["industrial", "warehouse", "site"],
      "sqft": 250000,
      "lod_level": 200,
      "disciplines": ["architecture", "site"],
      "thumbnail_url": "/proof/industrial_thumb.jpg",
      "pdf_url": "/proof/industrial_site.pdf",
      "snippet": "250,000 sqft industrial complex with 15-acre site survey. Combined aerial drone capture with interior scanning for complete property documentation.",
      "key_stats": {
        "sqft": 250000,
        "acres": 15,
        "method": "Drone + Terrestrial",
        "deliverable": "Site Model + Building"
      },
      "personas": ["BP1_Engineer", "BP2_Executive"],
      "uses": 12,
      "vault_to_meeting": 0.17,
      "last_used": "2026-01-08T00:00:00Z",
      "created_at": "2025-10-15T00:00:00Z"
    }
  ],
  "stats": {
    "total": 6,
    "by_type": {
      "case_study": 1,
      "lod_sample": 4,
      "whitepaper": 1
    },
    "total_uses": 223,
    "avg_vault_to_meeting": 0.20
  }
}
